latex_plot_styles/__init__.py
latex_plot_styles/configs.py
latex_plot_styles/figure_size.py
latex_plot_styles/matplotlib_style.py
latex_plot_styles-0.1.2.dist-info/LICENSE
latex_plot_styles-0.1.2.dist-info/METADATA
latex_plot_styles-0.1.2.dist-info/WHEEL
latex_plot_styles-0.1.2.dist-info/top_level.txt
latex_plot_styles-0.1.2.dist-info/RECORD
