Metadata-Version: 2.2
Name: latex_plot_styles
Version: 0.1.2
Summary: A simple helper package to adjust matplotlib plots to fit in LaTeX documents
Author: Tobias Weiß
Author-email: lebottel.team@gmail.com
License: MIT License
Classifier: Programming Language :: Python :: 3
Classifier: License :: OSI Approved :: MIT License
Classifier: Operating System :: OS Independent
Requires-Python: >=3.10
License-File: LICENSE
Requires-Dist: matplotlib>=3.10.1
Requires-Dist: pydantic>=2.10.6
Requires-Dist: seaborn>=0.13.2
